rainbear/__init__.py
rainbear/_core.abi3.so
rainbear/_core.pyi
rainbear-1.1.0b3.dist-info/METADATA
rainbear-1.1.0b3.dist-info/WHEEL
rainbear-1.1.0b3.dist-info/entry_points.txt
rainbear-1.1.0b3.dist-info/licenses/LICENSE
rainbear-1.1.0b3.dist-info/RECORD
