Metadata-Version: 2.4
Name: rainbear
Version: 1.1.0b3
Requires-Dist: polars==1.37.1
License-File: LICENSE
Summary: Build lazy Zarr scans with Polars
Keywords: zarr,polars,lazy
Author-email: Benjamin Sobel <ben-developer@opayq.com>
Requires-Python: >=3.12
